py_dutch_numerals/__init__.py
py_dutch_numerals/converter.py
py_dutch_numerals/logger.py
py_dutch_numerals/mock_logger.py
py_dutch_numerals/py.typed
py_dutch_numerals/generated/DutchNumbers.py
py_dutch_numerals/generated/DutchNumbersLexer.py
py_dutch_numerals/generated/DutchNumbersListener.py
py_dutch_numerals/generated/DutchNumbersVisitor.py
py_dutch_numerals-1.0.3.dist-info/LICENSE
py_dutch_numerals-1.0.3.dist-info/METADATA
py_dutch_numerals-1.0.3.dist-info/WHEEL
py_dutch_numerals-1.0.3.dist-info/top_level.txt
py_dutch_numerals-1.0.3.dist-info/RECORD
