Metadata-Version: 2.1
Name: py_dutch_numerals
Version: 1.0.3
Summary: A Python package to parse and convert Dutch counting numbers into numeric equivalents, supporting numbers up to one million.
Author-email: Jeroen Bloemscheer <info@jeroentechsolutions.uk>
License: European Union Public License 1.2 (EUPL-1.2)
Project-URL: Homepage, https://github.com/grootstebozewolf/py_dutch_numerals
Project-URL: Issues, https://github.com/grootstebozewolf/py_dutch_numerals/issues
Keywords: antlr,python,dutch,numbers,parser
Classifier: Programming Language :: Python :: 3
Classifier: License :: OSI Approved :: European Union Public Licence 1.2 (EUPL 1.2)
Classifier: Operating System :: OS Independent
Classifier: Typing :: Typed
Requires-Python: >=3.6
License-File: LICENSE
Requires-Dist: antlr4-python3-runtime
Provides-Extra: dev
Requires-Dist: behave ; extra == 'dev'
